NumpyMijiZhongwenDierBanChuyiFix1/README.md
NumpyMijiZhongwenDierBanChuyiFix1/__init__.py
NumpyMijiZhongwenDierBanChuyiFix1/__main__.py
NumpyMijiZhongwenDierBanChuyiFix1/file.epub
NumpyMijiZhongwenDierBanChuyiFix1/index.html
NumpyMijiZhongwenDierBanChuyiFix1/css/__init__.py
NumpyMijiZhongwenDierBanChuyiFix1/css/annotations.css
NumpyMijiZhongwenDierBanChuyiFix1/css/main.css
NumpyMijiZhongwenDierBanChuyiFix1/css/normalize.css
NumpyMijiZhongwenDierBanChuyiFix1/css/popup.css
NumpyMijiZhongwenDierBanChuyiFix1/font/__init__.py
NumpyMijiZhongwenDierBanChuyiFix1/font/fontello.eot
NumpyMijiZhongwenDierBanChuyiFix1/font/fontello.svg
NumpyMijiZhongwenDierBanChuyiFix1/font/fontello.ttf
NumpyMijiZhongwenDierBanChuyiFix1/font/fontello.woff
NumpyMijiZhongwenDierBanChuyiFix1/img/__init__.py
NumpyMijiZhongwenDierBanChuyiFix1/img/annotator-glyph-sprite.png
NumpyMijiZhongwenDierBanChuyiFix1/img/annotator-icon-sprite.png
NumpyMijiZhongwenDierBanChuyiFix1/img/apple-touch-icon.png
NumpyMijiZhongwenDierBanChuyiFix1/img/cancelfullscreen.png
NumpyMijiZhongwenDierBanChuyiFix1/img/close.png
NumpyMijiZhongwenDierBanChuyiFix1/img/fullscreen.png
NumpyMijiZhongwenDierBanChuyiFix1/img/loader.gif
NumpyMijiZhongwenDierBanChuyiFix1/img/menu-icon.png
NumpyMijiZhongwenDierBanChuyiFix1/img/save.png
NumpyMijiZhongwenDierBanChuyiFix1/img/saved.png
NumpyMijiZhongwenDierBanChuyiFix1/img/settings-s.png
NumpyMijiZhongwenDierBanChuyiFix1/img/settings.png
NumpyMijiZhongwenDierBanChuyiFix1/img/star.png
NumpyMijiZhongwenDierBanChuyiFix1/js/__init__.py
NumpyMijiZhongwenDierBanChuyiFix1/js/epub.js
NumpyMijiZhongwenDierBanChuyiFix1/js/epub.min.js
NumpyMijiZhongwenDierBanChuyiFix1/js/epub.min.map
NumpyMijiZhongwenDierBanChuyiFix1/js/hooks.min.js
NumpyMijiZhongwenDierBanChuyiFix1/js/hooks.min.map
NumpyMijiZhongwenDierBanChuyiFix1/js/reader.js
NumpyMijiZhongwenDierBanChuyiFix1/js/reader.js.map
NumpyMijiZhongwenDierBanChuyiFix1/js/reader.min.js
NumpyMijiZhongwenDierBanChuyiFix1/js/reader.min.map
numpy_miji_zhongwen_dier_ban_chuyi_fix1-2025.3.24.1.dist-info/METADATA
numpy_miji_zhongwen_dier_ban_chuyi_fix1-2025.3.24.1.dist-info/WHEEL
numpy_miji_zhongwen_dier_ban_chuyi_fix1-2025.3.24.1.dist-info/entry_points.txt
numpy_miji_zhongwen_dier_ban_chuyi_fix1-2025.3.24.1.dist-info/top_level.txt
numpy_miji_zhongwen_dier_ban_chuyi_fix1-2025.3.24.1.dist-info/RECORD
